waymo_open_dataset_tf_2_12_0-1.6.7.dist-info/RECORD
waymo_open_dataset_tf_2_12_0-1.6.7.dist-info/METADATA
waymo_open_dataset_tf_2_12_0-1.6.7.dist-info/WHEEL
waymo_open_dataset/dataset_pb2.py
waymo_open_dataset/label_pb2.py
waymo_open_dataset/utils/range_image_utils.py
waymo_open_dataset/utils/box_utils.py
waymo_open_dataset/utils/frame_utils.py
waymo_open_dataset/utils/keypoint_draw.py
waymo_open_dataset/utils/camera_segmentation_utils.py
waymo_open_dataset/utils/occupancy_flow_metrics.py
waymo_open_dataset/utils/transform_utils.py
waymo_open_dataset/utils/occupancy_flow_renderer.py
waymo_open_dataset/utils/occupancy_flow_grids.py
waymo_open_dataset/utils/occupancy_flow_vis.py
waymo_open_dataset/utils/womd_lidar_utils.py
waymo_open_dataset/utils/plot_maps.py
waymo_open_dataset/utils/womd_camera_utils.py
waymo_open_dataset/utils/geometry_utils.py
waymo_open_dataset/utils/occupancy_flow_data.py
waymo_open_dataset/utils/keypoint_data.py
waymo_open_dataset/utils/trajectory_utils.py
waymo_open_dataset/utils/sim_agents/submission_specs.py
waymo_open_dataset/utils/sim_agents/converters.py
waymo_open_dataset/utils/sim_agents/visualizations.py
waymo_open_dataset/utils/sim_agents/test_utils.py
waymo_open_dataset/utils/sim_agents/testdata/test_config.textproto
waymo_open_dataset/utils/sim_agents/testdata/test_config_dependent_timesteps.textproto
waymo_open_dataset/utils/sim_agents/testdata/test_submission.binproto
waymo_open_dataset/utils/compression/tiling.py
waymo_open_dataset/utils/compression/delta_encoder.py
waymo_open_dataset/utils/compression/pca_codec.py
waymo_open_dataset/protos/motion_metrics_pb2.py
waymo_open_dataset/protos/box_pb2.py
waymo_open_dataset/protos/map_pb2.py
waymo_open_dataset/protos/vector_pb2.py
waymo_open_dataset/protos/metrics_pb2.py
waymo_open_dataset/protos/end_to_end_driving_data_pb2.py
waymo_open_dataset/protos/end_to_end_driving_submission_pb2.py
waymo_open_dataset/protos/motion_submission_pb2.py
waymo_open_dataset/protos/occupancy_flow_submission_pb2.py
waymo_open_dataset/protos/segmentation_metrics_pb2.py
