Metadata-Version: 2.1
Name: waymo-open-dataset-tf-2-12-0
Home-page: https://github.com/waymo-research/waymo-open-dataset
Classifier: Development Status :: 5 - Production/Stable
Classifier: Intended Audience :: Developers
Classifier: Intended Audience :: Education
Classifier: Intended Audience :: Science/Research
Classifier: License :: OSI Approved :: Apache Software License
Classifier: Programming Language :: Python :: 3.10
Classifier: Topic :: Scientific/Engineering
Classifier: Topic :: Scientific/Engineering :: Artificial Intelligence
Classifier: Topic :: Software Development
Classifier: Topic :: Software Development :: Libraries
Classifier: Topic :: Software Development :: Libraries :: Python Modules
Requires-Dist: absl-py==1.4.0
Requires-Dist: dask[dataframe]==2023.3.1
Requires-Dist: einsum==0.3.0
Requires-Dist: google-auth==2.16.2
Requires-Dist: immutabledict==2.2.0
Requires-Dist: jax==0.4.13
Requires-Dist: jaxlib==0.4.13
Requires-Dist: matplotlib==3.6.1
Requires-Dist: numpy==1.23.5
Requires-Dist: pandas==1.5.3
Requires-Dist: pillow==9.2.0
Requires-Dist: plotly==5.13.1
Requires-Dist: pyarrow==16.0.0
Requires-Dist: scikit-image==0.20.0
Requires-Dist: scikit-learn==1.2.2
Requires-Dist: setuptools==67.6.0
Requires-Dist: tensorflow==2.13
Requires-Dist: tensorflow_probability==0.21.0
Requires-Dist: visu3d==1.5.1
Requires-Dist: dacite==1.8.1
Version: 1.6.7
